pd2tfrecord.py
pd2tfrecord-0.2.dist-info/LICENSE
pd2tfrecord-0.2.dist-info/LICENSE.txt
pd2tfrecord-0.2.dist-info/METADATA
pd2tfrecord-0.2.dist-info/WHEEL
pd2tfrecord-0.2.dist-info/top_level.txt
pd2tfrecord-0.2.dist-info/RECORD
