Metadata-Version: 2.1
Name: pd2tfrecord
Version: 0.2
Summary: Library to convert pandas data frame to tfrecord and vice versa
Home-page: https://github.com/NitinAgg/pd2tfrecord
Author: Nitin Aggarwal
Author-email: nitin.agg1909@gmail.com
License: MIT
Download-URL: https://github.com/NitinAgg/pd2tfrecord/archive/v_02.tar.gz
Keywords: tensorflow tfrecord pandas dataframe tf.example
Platform: UNKNOWN
Classifier: Development Status :: 4 - Beta
Classifier: Intended Audience :: Developers
Classifier: Topic :: Software Development :: Build Tools
Classifier: License :: OSI Approved :: MIT License
Classifier: Programming Language :: Python :: 3
Classifier: Programming Language :: Python :: 3.6
Classifier: Programming Language :: Python :: 3.7
Classifier: Programming Language :: Python :: 3.8
Requires-Dist: tensorflow (>=2.0)
Requires-Dist: pandas
